Workbook

Sheet 🏠 Inicio
B2: 💰 FinanzPro
B3: Sistema Integral de Finanzas · Negocios · Inventario
B4: Versión 2025 · Elaborado para uso profesional y personal
B7: 📊 Dashboard | D7: Ver resumen financiero
B8: 💳 Transacciones | D8: Registra ingresos y gastos
B9: 📦 Inventario | D9: Control de stock
B10: 👥 Clientes/Deudas | D10: Cuentas por cobrar
B11: 📈 Informe Mensual | D11: Cierre mes a mes
B13: ✏️ DATOS DE LA EMPRESA / NEGOCIO
B14: Empresa / Nombre | D14: ← ingresa aquí
B15: RUC / NIT / CUIT | D15: ← ingresa aquí
B16: Responsable | D16: ← ingresa aquí
B17: Año Fiscal | D17: 2026

Sheet 📊 Dashboard
B2: 📊 DASHBOARD FINANCIERO
B3: =TODAY()
B5: 💰 INGRESOS TOTALES | E5: 💸 GASTOS TOTALES | H5: 📈 BALANCE NETO | K5: 📋 N° TRANSACCIONES | N5: ✅ PAGADAS
B6: =SUM('💳 Transacciones'!F3:F302) | E6: =SUM('💳 Transacciones'!G3:G302) | H6: =B6-D6 | K6: =COUNTA('💳 Transacciones'!B3:B302) | N6: =COUNTIF('💳 Transacciones'!I3:I302,"Pagado")
B8: RESUMEN POR MES
B9: Mes | C9: Ingresos | D9: Gastos | E9: Balance | F9: Margen %
B10: Enero | C10: =SUMPRODUCT((MONTH('💳 Transacciones'!B$3:B$302)=1)*(YEAR('💳 Transacciones'!B$3:B$302)=YEAR(TODAY()))*'💳 Transacciones'!F$3:F$302) | D10: =SUMPRODUCT((MONTH('💳 Transacciones'!B$3:B$302)=1)*(YEAR('💳 Transacciones'!B$3:B$302)=YEAR(TODAY()))*'💳 Transacciones'!G$3:G$302) | E10: =C10-D10 | F10: =IFERROR((C10-D10)/C10,0)
B11: Febrero | C11: =SUMPRODUCT((MONTH('💳 Transacciones'!B$3:B$302)=2)*(YEAR('💳 Transacciones'!B$3:B$302)=YEAR(TODAY()))*'💳 Transacciones'!F$3:F$302) | D11: =SUMPRODUCT((MONTH('💳 Transacciones'!B$3:B$302)=2)*(YEAR('💳 Transacciones'!B$3:B$302)=YEAR(TODAY()))*'💳 Transacciones'!G$3:G$302) | E11: =C11-D11 | F11: =IFERROR((C11-D11)/C11,0)
B12: Marzo | C12: =SUMPRODUCT((MONTH('💳 Transacciones'!B$3:B$302)=3)*(YEAR('💳 Transacciones'!B$3:B$302)=YEAR(TODAY()))*'💳 Transacciones'!F$3:F$302) | D12: =SUMPRODUCT((MONTH('💳 Transacciones'!B$3:B$302)=3)*(YEAR('💳 Transacciones'!B$3:B$302)=YEAR(TODAY()))*'💳 Transacciones'!G$3:G$302) | E12: =C12-D12 | F12: =IFERROR((C12-D12)/C12,0)
B13: Abril | C13: =SUMPRODUCT((MONTH('💳 Transacciones'!B$3:B$302)=4)*(YEAR('💳 Transacciones'!B$3:B$302)=YEAR(TODAY()))*'💳 Transacciones'!F$3:F$302) | D13: =SUMPRODUCT((MONTH('💳 Transacciones'!B$3:B$302)=4)*(YEAR('💳 Transacciones'!B$3:B$302)=YEAR(TODAY()))*'💳 Transacciones'!G$3:G$302) | E13: =C13-D13 | F13: =IFERROR((C13-D13)/C13,0)
B14: Mayo | C14: =SUMPRODUCT((MONTH('💳 Transacciones'!B$3:B$302)=5)*(YEAR('💳 Transacciones'!B$3:B$302)=YEAR(TODAY()))*'💳 Transacciones'!F$3:F$302) | D14: =SUMPRODUCT((MONTH('💳 Transacciones'!B$3:B$302)=5)*(YEAR('💳 Transacciones'!B$3:B$302)=YEAR(TODAY()))*'💳 Transacciones'!G$3:G$302) | E14: =C14-D14 | F14: =IFERROR((C14-D14)/C14,0)
B15: Junio | C15: =SUMPRODUCT((MONTH('💳 Transacciones'!B$3:B$302)=6)*(YEAR('💳 Transacciones'!B$3:B$302)=YEAR(TODAY()))*'💳 Transacciones'!F$3:F$302) | D15: =SUMPRODUCT((MONTH('💳 Transacciones'!B$3:B$302)=6)*(YEAR('💳 Transacciones'!B$3:B$302)=YEAR(TODAY()))*'💳 Transacciones'!G$3:G$302) | E15: =C15-D15 | F15: =IFERROR((C15-D15)/C15,0)
B16: Julio | C16: =SUMPRODUCT((MONTH('💳 Transacciones'!B$3:B$302)=7)*(YEAR('💳 Transacciones'!B$3:B$302)=YEAR(TODAY()))*'💳 Transacciones'!F$3:F$302) | D16: =SUMPRODUCT((MONTH('💳 Transacciones'!B$3:B$302)=7)*(YEAR('💳 Transacciones'!B$3:B$302)=YEAR(TODAY()))*'💳 Transacciones'!G$3:G$302) | E16: =C16-D16 | F16: =IFERROR((C16-D16)/C16,0)
B17: Agosto | C17: =SUMPRODUCT((MONTH('💳 Transacciones'!B$3:B$302)=8)*(YEAR('💳 Transacciones'!B$3:B$302)=YEAR(TODAY()))*'💳 Transacciones'!F$3:F$302) | D17: =SUMPRODUCT((MONTH('💳 Transacciones'!B$3:B$302)=8)*(YEAR('💳 Transacciones'!B$3:B$302)=YEAR(TODAY()))*'💳 Transacciones'!G$3:G$302) | E17: =C17-D17 | F17: =IFERROR((C17-D17)/C17,0)
B18: Septiembre | C18: =SUMPRODUCT((MONTH('💳 Transacciones'!B$3:B$302)=9)*(YEAR('💳 Transacciones'!B$3:B$302)=YEAR(TODAY()))*'💳 Transacciones'!F$3:F$302) | D18: =SUMPRODUCT((MONTH('💳 Transacciones'!B$3:B$302)=9)*(YEAR('💳 Transacciones'!B$3:B$302)=YEAR(TODAY()))*'💳 Transacciones'!G$3:G$302) | E18: =C18-D18 | F18: =IFERROR((C18-D18)/C18,0)
B19: Octubre | C19: =SUMPRODUCT((MONTH('💳 Transacciones'!B$3:B$302)=10)*(YEAR('💳 Transacciones'!B$3:B$302)=YEAR(TODAY()))*'💳 Transacciones'!F$3:F$302) | D19: =SUMPRODUCT((MONTH('💳 Transacciones'!B$3:B$302)=10)*(YEAR('💳 Transacciones'!B$3:B$302)=YEAR(TODAY()))*'💳 Transacciones'!G$3:G$302) | E19: =C19-D19 | F19: =IFERROR((C19-D19)/C19,0)
B20: Noviembre | C20: =SUMPRODUCT((MONTH('💳 Transacciones'!B$3:B$302)=11)*(YEAR('💳 Transacciones'!B$3:B$302)=YEAR(TODAY()))*'💳 Transacciones'!F$3:F$302) | D20: =SUMPRODUCT((MONTH('💳 Transacciones'!B$3:B$302)=11)*(YEAR('💳 Transacciones'!B$3:B$302)=YEAR(TODAY()))*'💳 Transacciones'!G$3:G$302) | E20: =C20-D20 | F20: =IFERROR((C20-D20)/C20,0)
B21: Diciembre | C21: =SUMPRODUCT((MONTH('💳 Transacciones'!B$3:B$302)=12)*(YEAR('💳 Transacciones'!B$3:B$302)=YEAR(TODAY()))*'💳 Transacciones'!F$3:F$302) | D21: =SUMPRODUCT((MONTH('💳 Transacciones'!B$3:B$302)=12)*(YEAR('💳 Transacciones'!B$3:B$302)=YEAR(TODAY()))*'💳 Transacciones'!G$3:G$302) | E21: =C21-D21 | F21: =IFERROR((C21-D21)/C21,0)
B22: TOTAL AÑO | C22: =SUM(C10:C21) | D22: =SUM(D10:D21) | E22: =SUM(E10:E21) | F22: =IFERROR(E22/C22,0)
I24: GRÁFICO INGRESOS vs GASTOS
B40: TOP CATEGORÍAS DE GASTO
B41: Categoría | C41: Total Gasto | D41: % del Total
B42: Compra de Mercadería | C42: =SUMPRODUCT(('💳 Transacciones'!$E$3:$E$302="Compra de Mercadería")*'💳 Transacciones'!$G$3:$G$302) | D42: =IFERROR(C42/SUM($C$42:$C$52),0)
B43: Sueldos y Salarios | C43: =SUMPRODUCT(('💳 Transacciones'!$E$3:$E$302="Sueldos y Salarios")*'💳 Transacciones'!$G$3:$G$302) | D43: =IFERROR(C43/SUM($C$42:$C$52),0)
B44: Alquiler Local | C44: =SUMPRODUCT(('💳 Transacciones'!$E$3:$E$302="Alquiler Local")*'💳 Transacciones'!$G$3:$G$302) | D44: =IFERROR(C44/SUM($C$42:$C$52),0)
B45: Servicios (Agua/Luz/Internet) | C45: =SUMPRODUCT(('💳 Transacciones'!$E$3:$E$302="Servicios (Agua/Luz/Internet)")*'💳 Transacciones'!$G$3:$G$302) | D45: =IFERROR(C45/SUM($C$42:$C$52),0)
B46: Publicidad y Marketing | C46: =SUMPRODUCT(('💳 Transacciones'!$E$3:$E$302="Publicidad y Marketing")*'💳 Transacciones'!$G$3:$G$302) | D46: =IFERROR(C46/SUM($C$42:$C$52),0)
B47: Transporte y Envíos | C47: =SUMPRODUCT(('💳 Transacciones'!$E$3:$E$302="Transporte y Envíos")*'💳 Transacciones'!$G$3:$G$302) | D47: =IFERROR(C47/SUM($C$42:$C$52),0)
B48: Mantenimiento | C48: =SUMPRODUCT(('💳 Transacciones'!$E$3:$E$302="Mantenimiento")*'💳 Transacciones'!$G$3:$G$302) | D48: =IFERROR(C48/SUM($C$42:$C$52),0)
B49: Impuestos y Tributos | C49: =SUMPRODUCT(('💳 Transacciones'!$E$3:$E$302="Impuestos y Tributos")*'💳 Transacciones'!$G$3:$G$302) | D49: =IFERROR(C49/SUM($C$42:$C$52),0)
B50: Materiales y Suministros | C50: =SUMPRODUCT(('💳 Transacciones'!$E$3:$E$302="Materiales y Suministros")*'💳 Transacciones'!$G$3:$G$302) | D50: =IFERROR(C50/SUM($C$42:$C$52),0)
B51: Préstamo / Cuota | C51: =SUMPRODUCT(('💳 Transacciones'!$E$3:$E$302="Préstamo / Cuota")*'💳 Transacciones'!$G$3:$G$302) | D51: =IFERROR(C51/SUM($C$42:$C$52),0)
B52: Otros Gastos | C52: =SUMPRODUCT(('💳 Transacciones'!$E$3:$E$302="Otros Gastos")*'💳 Transacciones'!$G$3:$G$302) | D52: =IFERROR(C52/SUM($C$42:$C$52),0)

Sheet 💳 Transacciones
A1: 💳 REGISTRO DE TRANSACCIONES
A2: # | B2: Fecha | C2: Tipo | D2: Descripción | E2: Categoría | F2: Ingreso | G2: Gasto | H2: Método de Pago | I2: Estado | J2: Comprobante | K2: Referencia | L2: Notas
A3: 1
A4: 2
A5: 3
A6: 4
A7: 5
A8: 6
A9: 7
A10: 8
A11: 9
A12: 10
A13: 11
A14: 12
... A302: 300
F303: =SUM(F3:F302) | G303: =SUM(G3:G302) | H303: BALANCE → | I303: =F303-G303

Sheet 📦 Inventario
A1: 📦 CONTROL DE INVENTARIO
A2: # | B2: Código | C2: Producto / Descripción | D2: Categoría | E2: Unidad | F2: Stock Mínimo | G2: Stock Actual | H2: Precio Compra | I2: Precio Venta | J2: Valor Inventario | K2: Estado Stock | L2: Proveedor | M2: Notas
A3: 1 | J3: =IF(G3>0,G3*H3,"") | K3: =IF(G3="","",IF(G3=0,"🔴 SIN STOCK",IF(G3<=F3,"🟡 BAJO","🟢 OK")))
A4: 2 | J4: =IF(G4>0,G4*H4,"") | K4: =IF(G4="","",IF(G4=0,"🔴 SIN STOCK",IF(G4<=F4,"🟡 BAJO","🟢 OK")))
A5: 3 | J5: =IF(G5>0,G5*H5,"") | K5: =IF(G5="","",IF(G5=0,"🔴 SIN STOCK",IF(G5<=F5,"🟡 BAJO","🟢 OK")))
A6: 4 | J6: =IF(G6>0,G6*H6,"") | K6: =IF(G6="","",IF(G6=0,"🔴 SIN STOCK",IF(G6<=F6,"🟡 BAJO","🟢 OK")))
A7: 5 | J7: =IF(G7>0,G7*H7,"") | K7: =IF(G7="","",IF(G7=0,"🔴 SIN STOCK",IF(G7<=F7,"🟡 BAJO","🟢 OK")))
A8: 6 | J8: =IF(G8>0,G8*H8,"") | K8: =IF(G8="","",IF(G8=0,"🔴 SIN STOCK",IF(G8<=F8,"🟡 BAJO","🟢 OK")))
A9: 7 | J9: =IF(G9>0,G9*H9,"") | K9: =IF(G9="","",IF(G9=0,"🔴 SIN STOCK",IF(G9<=F9,"🟡 BAJO","🟢 OK")))
A10: 8 | J10: =IF(G10>0,G10*H10,"") | K10: =IF(G10="","",IF(G10=0,"🔴 SIN STOCK",IF(G10<=F10,"🟡 BAJO","🟢 OK")))
A11: 9 | J11: =IF(G11>0,G11*H11,"") | K11: =IF(G11="","",IF(G11=0,"🔴 SIN STOCK",IF(G11<=F11,"🟡 BAJO","🟢 OK")))
A12: 10 | J12: =IF(G12>0,G12*H12,"") | K12: =IF(G12="","",IF(G12=0,"🔴 SIN STOCK",IF(G12<=F12,"🟡 BAJO","🟢 OK")))
A13: 11 | J13: =IF(G13>0,G13*H13,"") | K13: =IF(G13="","",IF(G13=0,"🔴 SIN STOCK",IF(G13<=F13,"🟡 BAJO","🟢 OK")))
A14: 12 | J14: =IF(G14>0,G14*H14,"") | K14: =IF(G14="","",IF(G14=0,"🔴 SIN STOCK",IF(G14<=F14,"🟡 BAJO","🟢 OK")))
... A202: 200 | J202: =IF(G202>0,G202*H202,"") | K202: =IF(G202="","",IF(G202=0,"🔴 SIN STOCK",IF(G202<=F202,"🟡 BAJO","🟢 OK")))
I203: VALOR TOTAL → | J203: =SUM(J3:J202)

Sheet 👥 Clientes
A1: 👥 CLIENTES · CUENTAS POR COBRAR
A2: # | B2: Cliente / Razón Social | C2: Contacto | D2: Concepto | E2: Fecha Emisión | F2: Fecha Vencimiento | G2: Monto Total | H2: Monto Pagado | I2: Saldo Pendiente | J2: Estado | K2: Días Vencidos | L2: Notas
A3: 1 | I3: =IF(G3>0,G3-H3,"") | K3: =IF(F3="","",IF(I3>0,MAX(0,TODAY()-F3),""))
A4: 2 | I4: =IF(G4>0,G4-H4,"") | K4: =IF(F4="","",IF(I4>0,MAX(0,TODAY()-F4),""))
A5: 3 | I5: =IF(G5>0,G5-H5,"") | K5: =IF(F5="","",IF(I5>0,MAX(0,TODAY()-F5),""))
A6: 4 | I6: =IF(G6>0,G6-H6,"") | K6: =IF(F6="","",IF(I6>0,MAX(0,TODAY()-F6),""))
A7: 5 | I7: =IF(G7>0,G7-H7,"") | K7: =IF(F7="","",IF(I7>0,MAX(0,TODAY()-F7),""))
A8: 6 | I8: =IF(G8>0,G8-H8,"") | K8: =IF(F8="","",IF(I8>0,MAX(0,TODAY()-F8),""))
A9: 7 | I9: =IF(G9>0,G9-H9,"") | K9: =IF(F9="","",IF(I9>0,MAX(0,TODAY()-F9),""))
A10: 8 | I10: =IF(G10>0,G10-H10,"") | K10: =IF(F10="","",IF(I10>0,MAX(0,TODAY()-F10),""))
A11: 9 | I11: =IF(G11>0,G11-H11,"") | K11: =IF(F11="","",IF(I11>0,MAX(0,TODAY()-F11),""))
A12: 10 | I12: =IF(G12>0,G12-H12,"") | K12: =IF(F12="","",IF(I12>0,MAX(0,TODAY()-F12),""))
A13: 11 | I13: =IF(G13>0,G13-H13,"") | K13: =IF(F13="","",IF(I13>0,MAX(0,TODAY()-F13),""))
A14: 12 | I14: =IF(G14>0,G14-H14,"") | K14: =IF(F14="","",IF(I14>0,MAX(0,TODAY()-F14),""))
... A152: 150 | I152: =IF(G152>0,G152-H152,"") | K152: =IF(F152="","",IF(I152>0,MAX(0,TODAY()-F152),""))
A155: RESUMEN
A156: Total Facturado | G156: =SUM(G3:G152)
A157: Total Cobrado | G157: =SUM(H3:H152)
A158: Saldo Pendiente | G158: =SUM(I3:I152)
A159: Cuentas Vencidas | G159: =COUNTIF(J3:J152,"Vencido")

Sheet 📈 Informe Mensual
B2: 📈 INFORME DE CIERRE MENSUAL
B3: Selecciona Mes:
B4: 3 | C4: (1=Ene … 12=Dic)
B5: Año: | C5: 2026
B7: RESUMEN DEL MES SELECCIONADO
B8: 💰 INGRESOS | D8: 💸 GASTOS | F8: 📈 BALANCE | H8: 📋 MOVIMIENTOS
B9: =SUMPRODUCT((MONTH('💳 Transacciones'!B$3:B$302)=B4)*(YEAR('💳 Transacciones'!B$3:B$302)=C5)*'💳 Transacciones'!F$3:F$302) | D9: =SUMPRODUCT((MONTH('💳 Transacciones'!B$3:B$302)=B4)*(YEAR('💳 Transacciones'!B$3:B$302)=C5)*'💳 Transacciones'!G$3:G$302) | F9: =C8-E8 | H9: =SUMPRODUCT((MONTH('💳 Transacciones'!B$3:B$302)=B4)*(YEAR('💳 Transacciones'!B$3:B$302)=C5)*('💳 Transacciones'!B$3:B$302<>""))
B11: DETALLE DE GASTOS POR CATEGORÍA
B12: Categoría | C12: Monto | D12: % del Total
B13: Compra de Mercadería | C13: =SUMPRODUCT((MONTH('💳 Transacciones'!$B$3:$B$302)=B4)*(YEAR('💳 Transacciones'!$B$3:$B$302)=C5)*('💳 Transacciones'!$E$3:$E$302="Compra de Mercadería")*'💳 Transacciones'!$G$3:$G$302) | D13: =IFERROR(C13/SUM($C$13:$C$23),0)
B14: Sueldos y Salarios | C14: =SUMPRODUCT((MONTH('💳 Transacciones'!$B$3:$B$302)=B4)*(YEAR('💳 Transacciones'!$B$3:$B$302)=C5)*('💳 Transacciones'!$E$3:$E$302="Sueldos y Salarios")*'💳 Transacciones'!$G$3:$G$302) | D14: =IFERROR(C14/SUM($C$13:$C$23),0)
B15: Alquiler Local | C15: =SUMPRODUCT((MONTH('💳 Transacciones'!$B$3:$B$302)=B4)*(YEAR('💳 Transacciones'!$B$3:$B$302)=C5)*('💳 Transacciones'!$E$3:$E$302="Alquiler Local")*'💳 Transacciones'!$G$3:$G$302) | D15: =IFERROR(C15/SUM($C$13:$C$23),0)
B16: Servicios (Agua/Luz/Internet) | C16: =SUMPRODUCT((MONTH('💳 Transacciones'!$B$3:$B$302)=B4)*(YEAR('💳 Transacciones'!$B$3:$B$302)=C5)*('💳 Transacciones'!$E$3:$E$302="Servicios (Agua/Luz/Internet)")*'💳 Transacciones'!$G$3:$G$302) | D16: =IFERROR(C16/SUM($C$13:$C$23),0)
B17: Publicidad y Marketing | C17: =SUMPRODUCT((MONTH('💳 Transacciones'!$B$3:$B$302)=B4)*(YEAR('💳 Transacciones'!$B$3:$B$302)=C5)*('💳 Transacciones'!$E$3:$E$302="Publicidad y Marketing")*'💳 Transacciones'!$G$3:$G$302) | D17: =IFERROR(C17/SUM($C$13:$C$23),0)
B18: Transporte y Envíos | C18: =SUMPRODUCT((MONTH('💳 Transacciones'!$B$3:$B$302)=B4)*(YEAR('💳 Transacciones'!$B$3:$B$302)=C5)*('💳 Transacciones'!$E$3:$E$302="Transporte y Envíos")*'💳 Transacciones'!$G$3:$G$302) | D18: =IFERROR(C18/SUM($C$13:$C$23),0)
B19: Mantenimiento | C19: =SUMPRODUCT((MONTH('💳 Transacciones'!$B$3:$B$302)=B4)*(YEAR('💳 Transacciones'!$B$3:$B$302)=C5)*('💳 Transacciones'!$E$3:$E$302="Mantenimiento")*'💳 Transacciones'!$G$3:$G$302) | D19: =IFERROR(C19/SUM($C$13:$C$23),0)
B20: Impuestos y Tributos | C20: =SUMPRODUCT((MONTH('💳 Transacciones'!$B$3:$B$302)=B4)*(YEAR('💳 Transacciones'!$B$3:$B$302)=C5)*('💳 Transacciones'!$E$3:$E$302="Impuestos y Tributos")*'💳 Transacciones'!$G$3:$G$302) | D20: =IFERROR(C20/SUM($C$13:$C$23),0)
B21: Materiales y Suministros | C21: =SUMPRODUCT((MONTH('💳 Transacciones'!$B$3:$B$302)=B4)*(YEAR('💳 Transacciones'!$B$3:$B$302)=C5)*('💳 Transacciones'!$E$3:$E$302="Materiales y Suministros")*'💳 Transacciones'!$G$3:$G$302) | D21: =IFERROR(C21/SUM($C$13:$C$23),0)
B22: Préstamo / Cuota | C22: =SUMPRODUCT((MONTH('💳 Transacciones'!$B$3:$B$302)=B4)*(YEAR('💳 Transacciones'!$B$3:$B$302)=C5)*('💳 Transacciones'!$E$3:$E$302="Préstamo / Cuota")*'💳 Transacciones'!$G$3:$G$302) | D22: =IFERROR(C22/SUM($C$13:$C$23),0)
B23: Otros Gastos | C23: =SUMPRODUCT((MONTH('💳 Transacciones'!$B$3:$B$302)=B4)*(YEAR('💳 Transacciones'!$B$3:$B$302)=C5)*('💳 Transacciones'!$E$3:$E$302="Otros Gastos")*'💳 Transacciones'!$G$3:$G$302) | D23: =IFERROR(C23/SUM($C$13:$C$23),0)

Sheet ❓ Instrucciones
B2: ❓ GUÍA DE USO — FinanzPro
B4: 🏠 Inicio | C4: Completa los datos de tu empresa o negocio en la hoja Inicio.
B5: 💳 Transacciones | C5: Registra CADA movimiento: fecha, tipo (Ingreso/Gasto), descripción, categoría, monto y método de pago.
B6: 📊 Dashboard | C6: El dashboard se actualiza automáticamente con tus datos. No edites las celdas con fórmulas (fondo azul/verde/rojo).
B7: 📦 Inventario | C7: Para negocios/bodegas: registra tus productos, stock mínimo y actual. El semáforo 🟢🟡🔴 se actualiza solo.
B8: 👥 Clientes | C8: Registra tus cuentas por cobrar. Ingresa fecha de vencimiento y el saldo pendiente se calcula automático.
B9: 📈 Informe Mensual | C9: Cambia el número de mes en celda B4 (1-12) para ver el cierre de cualquier mes del año.
B10: 💡 Tip: Categorías | C10: Usa las categorías predefinidas del desplegable para que el Dashboard agrupe correctamente.
B11: 💡 Tip: Fechas | C11: Siempre ingresa fechas en formato DD/MM/YYYY o usando el selector de fecha de Excel.
B12: 💡 Tip: Backup | C12: Guarda una copia del archivo al final de cada mes con el nombre: FinanzPro_MMYYYY.xlsx
B13: ⚠️ Importante | C13: NO elimines las filas de encabezado ni las hojas de sistema (⚙ Listas). Puedes agregar filas antes de la fila TOTALES.
B15: © FinanzPro 2025 · Plantilla Profesional de Gestión Financiera

Sheet ⚙ Listas
A1: Cat_Ingreso | B1: Cat_Gasto | C1: Metodo | D1: Estado | E1: Tipo | F1: Unidad
A2: Ventas de Productos | B2: Compra de Mercadería | C2: Efectivo | D2: Pagado | E2: Ingreso | F2: Unidad
A3: Ventas de Servicios | B3: Sueldos y Salarios | C3: Transferencia | D3: Pendiente | E3: Gasto | F3: Kg
A4: Comisiones | B4: Alquiler Local | C4: Tarjeta de Crédito | D4: Anulado | F4: Lt
A5: Alquileres | B5: Servicios (Agua/Luz/Internet) | C5: Tarjeta de Débito | F5: Caja
A6: Intereses | B6: Publicidad y Marketing | C6: Cheque | F6: Paquete
A7: Préstamos Recibidos | B7: Transporte y Envíos | C7: Yape/Plin | F7: Docena
A8: Devoluciones | B8: Mantenimiento | C8: Nequi | F8: Metro
A9: Otros Ingresos | B9: Impuestos y Tributos | C9: Daviplata | F9: Par
B10: Materiales y Suministros | C10: Otro | F10: Bolsa
B11: Préstamo / Cuota
B12: Otros Gastos
